todo_cli_ultra/__init__.py
todo_cli_ultra/constants.py
todo_cli_ultra/main.py
todo_cli_ultra-0.2.7.dist-info/METADATA
todo_cli_ultra-0.2.7.dist-info/WHEEL
todo_cli_ultra-0.2.7.dist-info/entry_points.txt
todo_cli_ultra-0.2.7.dist-info/top_level.txt
todo_cli_ultra-0.2.7.dist-info/RECORD
