Metadata-Version: 2.4
Name: todo-cli-ultra
Version: 0.2.7
Summary: CLI tool for todo app
Requires-Python: >=3.12
Requires-Dist: typer>=0.16.0
